Keystack
