Metadata-Version: 2.4
Name: keystack
Version: 0.41.44.0
Summary: Keystack automation framework for managing test script executions
Author: Hubert Gee
Author-email: hubert.gee@keysight.com
Classifier: Programming Language :: Python :: 3 :: Only
Classifier: Operating System :: POSIX :: Linux
Requires-Dist: requests==2.32.5
Requires-Dist: boto3==1.34.114
Requires-Dist: botocore==1.34.114
Requires-Dist: click==8.1.6
Requires-Dist: django==5.2.10
Requires-Dist: daphne==4.2.1
Requires-Dist: Exscript==2.6.28
Requires-Dist: pymongo==4.16.0
Requires-Dist: python-dotenv==1.2.1
Requires-Dist: djangorestframework==3.16.1
Requires-Dist: channels==4.3.2
Requires-Dist: drf-yasg==1.21.14
Requires-Dist: pytz==2022.2.1
Requires-Dist: PyYaml==6.0.3
Requires-Dist: django-filter
Requires-Dist: jira==3.3.2
Requires-Dist: httpx==0.24.0
Requires-Dist: gunicorn==21.2.0
Requires-Dist: paramiko==3.4.0
Requires-Dist: pydantic==2.5.2
Requires-Dist: redis==7.1.0
Requires-Dist: watchdog==6.0.0
Requires-Dist: pytest==7.4.3
